osd/__init__.py
osd/dbus.py
osd/osd.py
osd-0.6.data/scripts/osdd
osd-0.6.dist-info/LICENSE
osd-0.6.dist-info/METADATA
osd-0.6.dist-info/WHEEL
osd-0.6.dist-info/top_level.txt
osd-0.6.dist-info/RECORD
