Metadata-Version: 2.1
Name: osd
Version: 0.6
Summary: A fully featured notification daemon
Home-page: https://gitlab.com/pcapriotti/osd
Author: Paolo Capriotti
Author-email: paolo@capriotti.io
License: BSD3
Platform: UNKNOWN
Classifier: License :: OSI Approved :: BSD License
Classifier: Programming Language :: Python :: 3
